rsockets2
